deksound-0.1.1.dist-info/METADATA
deksound-0.1.1.dist-info/WHEEL
deksound-0.1.1.dist-info/entry_points.txt
deksound/__init__.py
deksound/click/__entry__.py
deksound/click/__init__.py
deksound/core/__init__.py
deksound/core/res/failure.mp3
deksound/core/res/success.mp3
deksound-0.1.1.dist-info/RECORD
