Metadata-Version: 2.1
Name: deksound
Version: 0.1.1
Author-Email: sanzenwin <sanzenwin@gmail.com>
License: MIT
Requires-Python: >=3.10
Requires-Dist: typer<=0.9.0
Requires-Dist: just-playback<=0.1.8
